{
  "sentences": [
    {
      "finnish": "sytyttää lamppu",
      "english": "turn on the lamp"
    },
    {
      "finnish": "sammuttaa lamppu",
      "english": "turn off the lamp"
    },
    {
      "finnish": "käydä suihkussa",
      "english": "take a shower"
    },
    {
      "finnish": "mennä suihkuun",
      "english": "go to the shower"
    },
    {
      "finnish": "Laitan pyykit pesukoneeseen.",
      "english": "I put the laundry in the washing machine."
    },
    {
      "finnish": "Ripusta takki naulakkoon.",
      "english": "Hang the coat on the coat rack."
    },
    {
      "finnish": "Pyyhi jalat mattoon.",
      "english": "Wipe your feet on the mat."
    },
    {
      "finnish": "irtisanoa vuokrasopimus",
      "english": "terminate the lease agreement"
    },
    {
      "finnish": "Onko vapaita vuoroja?",
      "english": "Are there any available shifts?"
    },
    {
      "finnish": "Mitkä ajat ovat vapaana?",
      "english": "What times are you free?"
    },
    {
      "finnish": "Pidän tauon.",
      "english": "I'm taking a break."
    }
  ]
}